hmrb/__init__.py
hmrb/core.py
hmrb/lang.py
hmrb/node.py
hmrb/protobuffer.py
hmrb/response_pb2.py
hmrb-1.2.1.dist-info/METADATA
hmrb-1.2.1.dist-info/WHEEL
hmrb-1.2.1.dist-info/top_level.txt
hmrb-1.2.1.dist-info/RECORD
