Metadata-Version: 2.1
Name: hmrb
Version: 1.2.1
Summary: Hammurabi
Home-page: https://github.com/babylonhealth/hmrb
Author: Babylon Health
Author-email: kristian.boda@babylonhealth.com
License: Apache License 2.0
Platform: UNKNOWN
Classifier: Intended Audience :: Developers
Classifier: Operating System :: OS Independent
Classifier: Programming Language :: Python
Classifier: Programming Language :: Python :: 3
Requires-Dist: addict (==2.4.0)
Requires-Dist: protobuf (==3.19.3)
